clairmeta/__init__.py
clairmeta/cli.py
clairmeta/dcp.py
clairmeta/dcp_check.py
clairmeta/dcp_check_am.py
clairmeta/dcp_check_atmos.py
clairmeta/dcp_check_cpl.py
clairmeta/dcp_check_execution.py
clairmeta/dcp_check_global.py
clairmeta/dcp_check_isdcf_dcnc.py
clairmeta/dcp_check_picture.py
clairmeta/dcp_check_pkl.py
clairmeta/dcp_check_sign.py
clairmeta/dcp_check_sound.py
clairmeta/dcp_check_subtitle.py
clairmeta/dcp_check_utils.py
clairmeta/dcp_check_vol.py
clairmeta/dcp_parse.py
clairmeta/dcp_utils.py
clairmeta/exception.py
clairmeta/info.py
clairmeta/logger.py
clairmeta/profile.py
clairmeta/report.py
clairmeta/sequence.py
clairmeta/sequence_check.py
clairmeta/settings.py
clairmeta/utils/__init__.py
clairmeta/utils/crypto.py
clairmeta/utils/file.py
clairmeta/utils/isdcf.py
clairmeta/utils/probe.py
clairmeta/utils/sys.py
clairmeta/utils/time.py
clairmeta/utils/uuid.py
clairmeta/utils/xml.py
clairmeta-1.6.1.dist-info/licenses/LICENSE
clairmeta-1.6.1.dist-info/METADATA
clairmeta-1.6.1.dist-info/WHEEL
clairmeta-1.6.1.dist-info/top_level.txt
clairmeta-1.6.1.dist-info/RECORD
