Metadata-Version: 2.4
Name: clairmeta
Version: 1.6.1
Summary: ClairMeta is a python package for Digital Cinema Package (DCP) probing and checking.
Author-email: Rémi Achard <remiachard@gmail.com>
License: BSD-3-Clause
Project-URL: Repository, https://github.com/Ymagis/ClairMeta
Keywords: digital,cinema,dcp,dcdm,dsm,check,probe,smpte,interop
Classifier: Development Status :: 5 - Production/Stable
Classifier: Intended Audience :: Developers
Classifier: Topic :: Utilities
Classifier: Topic :: Multimedia :: Video
Classifier: Topic :: Software Development :: Libraries :: Python Modules
Classifier: License :: OSI Approved :: BSD License
Classifier: Programming Language :: Python :: 3
Classifier: Programming Language :: Python :: 3.8
Classifier: Programming Language :: Python :: 3.9
Classifier: Programming Language :: Python :: 3.10
Classifier: Programming Language :: Python :: 3.11
Classifier: Programming Language :: Python :: 3.12
Classifier: Programming Language :: Python :: 3.13
Requires-Python: >=3.8
License-File: LICENSE
Requires-Dist: cryptography>=44.0.0
Requires-Dist: dicttoxml>=1.7.16
Requires-Dist: freetype-py>=2.5.1
Requires-Dist: lxml>=5.3.0
Requires-Dist: pycountry>=24.6.1
Requires-Dist: python-dateutil>=2.9.0.post0
Requires-Dist: xmltodict>=0.14.2
Dynamic: license-file
